reem/__init__.py
reem/accessors.py
reem/connection.py
reem/marshalling.py
reem/utilities.py
reem-0.1.2.dist-info/LICENSE.txt
reem-0.1.2.dist-info/METADATA
reem-0.1.2.dist-info/WHEEL
reem-0.1.2.dist-info/top_level.txt
reem-0.1.2.dist-info/RECORD
