Metadata-Version: 2.1
Name: reem
Version: 0.1.2
Summary: Redis Extendable Efficient Middleware
Home-page: https://www.github.com/krishauser/reem
Author: Trishul Nagenalli and Kris Hauser
Author-email: hauser.kris@gmail.com
License: Apache 2.0
Platform: UNKNOWN
Requires-Dist: rejson
Requires-Dist: redis
Requires-Dist: six
Requires-Dist: numpy
